{
  "object_type": "player_prop_profile",
  "version": "v2",
  "slug": "jabari-smith-jr",
  "url": "https://sportsync-evidence.web.app/props/jabari-smith-jr",
  "league": "NBA",
  "season": "2025-26",
  "player_name": "Jabari Smith Jr.",
  "summary": "Jabari Smith Jr. — No strong signal — Top market by sample: Points 57.5% (73 GP)",
  "generated_at": "2026-03-29T01:26:49.597848+00:00",
  "hero_count": 0,
  "market_cards": [
    {
      "market": "points",
      "market_label": "Points",
      "direction": "none",
      "tier": "feature",
      "is_hero": false,
      "rate": 57.5,
      "record": "42-31",
      "gp": 73
    },
    {
      "market": "threes_made",
      "market_label": "Threes Made",
      "direction": "none",
      "tier": "feature",
      "is_hero": false,
      "rate": 54.8,
      "record": "40-33",
      "gp": 73
    },
    {
      "market": "rebounds",
      "market_label": "Rebounds",
      "direction": "none",
      "tier": "feature",
      "is_hero": false,
      "rate": 53.4,
      "record": "39-34",
      "gp": 73
    },
    {
      "market": "pra",
      "market_label": "Pts+Reb+Ast",
      "direction": "none",
      "tier": "feature",
      "is_hero": false,
      "rate": 50,
      "record": "26-26",
      "gp": 52
    },
    {
      "market": "assists",
      "market_label": "Assists",
      "direction": "none",
      "tier": "feature",
      "is_hero": false,
      "rate": 47.4,
      "record": "18-20",
      "gp": 38
    }
  ],
  "markets": {
    "points": {
      "baseline": {
        "rate": 57.5,
        "record": "42-31",
        "avg": 15.5,
        "median": 16,
        "gp": 73,
        "direction": "none",
        "tier": "feature",
        "is_hero": false
      },
      "current_line": {
        "line": 14.5,
        "rate": 50,
        "record": "10-10",
        "avg": 15.5,
        "gp": 20
      },
      "book_pricing_history": [
        {
          "book": "DraftKings",
          "line": 13.5,
          "rate": 62.5,
          "gp": 16
        },
        {
          "book": "DraftKings",
          "line": 14.5,
          "rate": 57.1,
          "gp": 14
        },
        {
          "book": "DraftKings",
          "line": 15.5,
          "rate": 70,
          "gp": 10
        },
        {
          "book": "FanDuel",
          "line": 14.5,
          "rate": 33.3,
          "gp": 6
        }
      ],
      "supporting_context": [
        {
          "label": "MID season",
          "rate": 46.2,
          "record": null,
          "gp": 13
        },
        {
          "label": "vs FAST pace",
          "rate": 45.5,
          "record": null,
          "gp": 11
        },
        {
          "label": "HOME",
          "rate": 50,
          "record": null,
          "gp": 10
        }
      ]
    },
    "threes_made": {
      "baseline": {
        "rate": 54.8,
        "record": "40-33",
        "avg": 2.3,
        "median": 2,
        "gp": 73,
        "direction": "none",
        "tier": "feature",
        "is_hero": false
      },
      "current_line": {
        "line": 1.5,
        "rate": 71.8,
        "record": "28-11",
        "avg": 2.2,
        "gp": 39
      },
      "book_pricing_history": [
        {
          "book": "DraftKings",
          "line": 1.5,
          "rate": 70,
          "gp": 30
        },
        {
          "book": "DraftKings",
          "line": 2.5,
          "rate": 33.3,
          "gp": 21
        },
        {
          "book": "FanDuel",
          "line": 1.5,
          "rate": 77.8,
          "gp": 9
        },
        {
          "book": "FanDuel",
          "line": 2.5,
          "rate": 33.3,
          "gp": 6
        }
      ],
      "supporting_context": [
        {
          "label": "HOME",
          "rate": 78.3,
          "record": null,
          "gp": 23
        },
        {
          "label": "vs FAST pace",
          "rate": 70,
          "record": null,
          "gp": 20
        },
        {
          "label": "Rest: 1",
          "rate": 77.8,
          "record": null,
          "gp": 18
        }
      ]
    },
    "rebounds": {
      "baseline": {
        "rate": 53.4,
        "record": "39-34",
        "avg": 6.8,
        "median": 7,
        "gp": 73,
        "direction": "none",
        "tier": "feature",
        "is_hero": false
      },
      "current_line": {
        "line": 6.5,
        "rate": 58.5,
        "record": "24-17",
        "avg": 6.7,
        "gp": 41
      },
      "book_pricing_history": [
        {
          "book": "DraftKings",
          "line": 6.5,
          "rate": 51.7,
          "gp": 29
        },
        {
          "book": "DraftKings",
          "line": 7.5,
          "rate": 25,
          "gp": 12
        },
        {
          "book": "FanDuel",
          "line": 6.5,
          "rate": 75,
          "gp": 12
        },
        {
          "book": "DraftKings",
          "line": 5.5,
          "rate": 63.6,
          "gp": 11
        }
      ],
      "supporting_context": [
        {
          "label": "HOME",
          "rate": 59.1,
          "record": null,
          "gp": 22
        },
        {
          "label": "vs FAST pace",
          "rate": 71.4,
          "record": null,
          "gp": 21
        },
        {
          "label": "MID season",
          "rate": 68.4,
          "record": null,
          "gp": 19
        }
      ]
    },
    "pra": {
      "baseline": {
        "rate": 50,
        "record": "26-26",
        "avg": 23.1,
        "median": 23,
        "gp": 52,
        "direction": "none",
        "tier": "feature",
        "is_hero": false
      },
      "current_line": {
        "line": 21.5,
        "rate": 57.1,
        "record": "8-6",
        "avg": 22.6,
        "gp": 14
      },
      "book_pricing_history": [
        {
          "book": "DraftKings",
          "line": 21.5,
          "rate": 61.5,
          "gp": 13
        },
        {
          "book": "DraftKings",
          "line": 23.5,
          "rate": 63.6,
          "gp": 11
        },
        {
          "book": "DraftKings",
          "line": 24.5,
          "rate": 50,
          "gp": 8
        },
        {
          "book": "DraftKings",
          "line": 22.5,
          "rate": 57.1,
          "gp": 7
        }
      ],
      "supporting_context": [
        {
          "label": "EARLY season",
          "rate": 55.6,
          "record": null,
          "gp": 9
        },
        {
          "label": "Rest: 1",
          "rate": 62.5,
          "record": null,
          "gp": 8
        },
        {
          "label": "AWAY",
          "rate": 50,
          "record": null,
          "gp": 8
        }
      ]
    },
    "assists": {
      "baseline": {
        "rate": 47.4,
        "record": "18-20",
        "avg": 1.7,
        "median": 2,
        "gp": 38,
        "direction": "none",
        "tier": "feature",
        "is_hero": false
      },
      "current_line": {
        "line": 1.5,
        "rate": 51.7,
        "record": "15-14",
        "avg": 1.6,
        "gp": 29
      },
      "book_pricing_history": [
        {
          "book": "DraftKings",
          "line": 1.5,
          "rate": 51.7,
          "gp": 29
        },
        {
          "book": "DraftKings",
          "line": 2.5,
          "rate": 28.6,
          "gp": 7
        }
      ],
      "supporting_context": [
        {
          "label": "HOME",
          "rate": 56.3,
          "record": null,
          "gp": 16
        },
        {
          "label": "Rest: 1",
          "rate": 53.3,
          "record": null,
          "gp": 15
        },
        {
          "label": "vs FAST pace",
          "rate": 57.1,
          "record": null,
          "gp": 14
        }
      ]
    }
  },
  "methodology": {
    "baseline": "All games for this player × market, across all books and lines.",
    "current_line": "Most common historical line (highest GP) across all sportsbooks.",
    "book_context": "Hit rate per sportsbook × line combination.",
    "supporting_context": "Venue, pace tier, rest days, season phase splits at the most common historical line.",
    "over_rate": "Overs / (overs + unders), pushes excluded.",
    "display_floor": "10 GP minimum. Feature tier: 30+ GP. Hero: 65%+ or 35%- over rate."
  }
}